time_decomp/decomposition.py
time_decomp/environmentaltrends.py
time_decomp/sarimax.py
time_decomp-2.0.1.dist-info/METADATA
time_decomp-2.0.1.dist-info/WHEEL
time_decomp-2.0.1.dist-info/licenses/LICENSE
time_decomp-2.0.1.dist-info/RECORD
