Metadata-Version: 2.4
Name: time-decomp
Version: 2.0.1
Summary: Time series decomposition plot trend and seasonality together
Project-URL: Homepage, https://github.com/AcaciaMan/time-decomp
Project-URL: Issues, https://github.com/AcaciaMan/time-decomp/issues
Author-email: AcaciaMan <11488694+AcaciaMan@users.noreply.github.com>
License-File: LICENSE
Classifier: License :: OSI Approved :: Apache Software License
Classifier: Operating System :: OS Independent
Classifier: Programming Language :: Python :: 3
